mnest/Entities.py
mnest/Environment.py
mnest/Laws.py
mnest/__init__.py
mnest/data/random_seed.txt
mnest-0.1.0.dist-info/LICENSE.txt
mnest-0.1.0.dist-info/METADATA
mnest-0.1.0.dist-info/WHEEL
mnest-0.1.0.dist-info/top_level.txt
mnest-0.1.0.dist-info/RECORD
