Metadata-Version: 2.1
Name: mnest
Version: 0.1.0
Summary: MNEST (Multi-agent Neuro Evolution Simulation Toolkit) is a software framework designed to model and study emergent behavior in complex systems
Home-page: https://github.com/Bluejee/SEAN
Author: Balakrishna Prabhu B N
Author-email: balakrishnaprabhu1999@gmail.com
License: GPL-3.0-or-later
Keywords: simulation,multi-agent,neuro-evolution,AI,ML,Biology,Physics,Computation,Complex Systems
Platform: UNKNOWN
Classifier: Programming Language :: Python :: 3
Classifier: Operating System :: OS Independent
Classifier: License :: OSI Approved :: GNU General Public License v3 (GPLv3)
Classifier: Intended Audience :: Education
Classifier: Intended Audience :: Developers
Classifier: Intended Audience :: Science/Research
Requires-Python: >=3.7
License-File: LICENSE.txt
Requires-Dist: numpy (==1.24.2)
Requires-Dist: pygame (==2.3.0)
Requires-Dist: scipy (==1.10.1)
